trame/__init__.py
trame/modules/__init__.py
trame/modules/color_opacity.py
trame/widgets/__init__.py
trame/widgets/color_opacity_editor.py
trame_color_opacity_editor/__init__.py
trame_color_opacity_editor/module/__init__.py
trame_color_opacity_editor/module/serve/trame_color_opacity_editor.css
trame_color_opacity_editor/module/serve/trame_color_opacity_editor.umd.js
trame_color_opacity_editor/widgets/__init__.py
trame_color_opacity_editor/widgets/internal/__init__.py
trame_color_opacity_editor-1.0.0.dist-info/METADATA
trame_color_opacity_editor-1.0.0.dist-info/WHEEL
trame_color_opacity_editor-1.0.0.dist-info/RECORD
