Metadata-Version: 2.4
Name: trame-color-opacity-editor
Version: 1.0.0
Summary: A trame package implementing the Paraview/Tomviz color-opacity editor.
Author: Alessandro Genova
License: Apache Software License
Keywords: Application,Framework,Interactive,Python,Web
Classifier: Development Status :: 5 - Production/Stable
Classifier: Environment :: Web Environment
Classifier: License :: OSI Approved :: Apache Software License
Classifier: Natural Language :: English
Classifier: Operating System :: OS Independent
Classifier: Programming Language :: Python :: 3 :: Only
Classifier: Topic :: Software Development :: Libraries :: Application Frameworks
Classifier: Topic :: Software Development :: Libraries :: Python Modules
Requires-Python: >=3.10
Requires-Dist: trame-client>=3.10
Provides-Extra: dev
Requires-Dist: codespell; extra == 'dev'
Requires-Dist: pre-commit; extra == 'dev'
Requires-Dist: pytest; extra == 'dev'
Requires-Dist: ruff; extra == 'dev'
